src/__init__.py
src/cli.py
src/exporter.py
src/help.py
src/http_server.py
src/test_cli.py
src/test_exporter.py
src/test_http_server.py
src/test_metrics.py
prometheus_exporter_celery-0.11.2.dist-info/LICENSE.md
prometheus_exporter_celery-0.11.2.dist-info/METADATA
prometheus_exporter_celery-0.11.2.dist-info/WHEEL
prometheus_exporter_celery-0.11.2.dist-info/RECORD
