Metadata-Version: 2.3
Name: prometheus-exporter-celery
Version: 0.11.2
Summary: 
License: MIT
Keywords: celery,task-processing,prometheus,grafana,monitoring
Author: Dani Hodovic
Author-email: dani.hodovic@gmail.com
Requires-Python: >=3.11,<3.13
Classifier: Framework :: Celery
Classifier: Framework :: Django
Classifier: License :: OSI Approved :: MIT License
Classifier: Programming Language :: Python :: 3
Classifier: Programming Language :: Python :: 3.11
Classifier: Programming Language :: Python :: 3.12
Classifier: Topic :: System :: Distributed Computing
Classifier: Topic :: System :: Monitoring
Classifier: Topic :: System :: Systems Administration
Requires-Dist: Flask (>=3.1.0,<4.0.0)
Requires-Dist: arrow (>=1.3.0,<2.0.0)
Requires-Dist: celery (>=5.5.2,<6.0.0)
Requires-Dist: click (>=8.1.8,<9.0.0)
Requires-Dist: loguru (>=0.7.3,<0.8.0)
Requires-Dist: pretty-errors (>=1.2.25,<2.0.0)
Requires-Dist: prometheus-client (>=0.21.1,<0.22.0)
Requires-Dist: redis (>=5.2.0,<6.0.0)
Requires-Dist: timy (>=0.4.2,<0.5.0)
Requires-Dist: waitress (>=3.0.2,<4.0.0)
Project-URL: Documentation, https://github.com/danihodovic/celery-exporter
Project-URL: Repository, https://github.com/danihodovic/celery-exporter
